my_anime_list_scraper/__init__.py
my_anime_list_scraper/cleaner.py
my_anime_list_scraper/extractor.py
my_anime_list_scraper/mysql_manager.py
my_anime_list_scraper/saver.py
my_anime_list_scraper/scraper.py
my_anime_list_scraper/scraper_types.py
my_anime_list_scraper/sql_queries.py
my_anime_list_scraper-0.0.56.dist-info/LICENSE
my_anime_list_scraper-0.0.56.dist-info/METADATA
my_anime_list_scraper-0.0.56.dist-info/WHEEL
my_anime_list_scraper-0.0.56.dist-info/top_level.txt
my_anime_list_scraper-0.0.56.dist-info/RECORD
