Metadata-Version: 2.1
Name: my-anime-list-scraper
Version: 0.0.56
Summary: A scraper for www.myanimelist.com
Home-page: https://github.com/koji98/my_anime_list_scraper
Author: Chidi Udeze
Author-email: chidiu98@gmail.com
License: UNKNOWN
Platform: UNKNOWN
Classifier: Programming Language :: Python :: 3
Classifier: License :: OSI Approved :: MIT License
Classifier: Operating System :: OS Independent
Requires-Python: >=3.6
Requires-Dist: beautifulsoup4 (==4.9.3)
Requires-Dist: mysql-connector-python (==8.0.22)
Requires-Dist: requests (==2.24.0)
